good_lang/__init__.py
good_lang/py.typed
good_lang/nlp/__init__.py
good_lang/nlp/utilities.py
good_lang/prompt/__init__.py
good_lang/prompt/prompt.py
good_lang/providers/__init__.py
good_lang/providers/litellm.py
good_lang-0.1.1.dist-info/METADATA
good_lang-0.1.1.dist-info/WHEEL
good_lang-0.1.1.dist-info/RECORD
