Metadata-Version: 2.3
Name: good-lang
Version: 0.1.1
Summary: Add your description here
Requires-Python: >=3.12
Requires-Dist: assemblyai>=0.34.0
Requires-Dist: ell-ai[anthropic]>=0.0.14
Requires-Dist: good-common>=0.1.7
Requires-Dist: instructor>=1.6.3
Requires-Dist: langfuse>=2.52.1
Requires-Dist: litellm>=1.52.5
Requires-Dist: prompt-toolkit>=3.0.48
Requires-Dist: unstructured>=0.16.5
